[{"fase":"Pagamento","documento":"2016DF800063","tipoDocumento":"Documento de Arrecadação de Receitas Federais (DARF) (DF)","data":"2016-01-29 00:00:00.0","orgaoSuperior":{"codigo":"26000","rotulo":"MINISTERIO DA EDUCACAO"},"orgao":{"codigo":"26234","rotulo":"UNIVERSIDADE FEDERAL DO ESPIRITO SANTO"},"unidadeGestora":{"codigo":"153048","rotulo":"RESTAURANTE CENTRAL DA UFES"},"gestao":{"codigo":"15225","rotulo":"UNIVERSIDADE FEDERAL DO ESPIRITO SANTO"},"favorecido":{"codigo":"10.518.100/0001-6","rotulo":"EMERSON JOSE TESCH - EPP"},"valor":"R$ 2.1600","observacao":"RETENÇÃO CONFORME IN RFB 1234/2012. REFERENTE PAGAMENTO NF 10222.","classificacaoEconomica":{"codigo":"3","rotulo":" Despesas Correntes"},"grupoDespesa":{"codigo":"3","rotulo":" Outras Despesas Correntes"},"modalidadeAplicacao":{"codigo":"90","rotulo":"Aplic. Diretas                                                (Gastos Diretos do Governo Federal)"},"elementoDespesa":{"codigo":"30","rotulo":"MATERIAL DE CONSUMO"},"documentosRelacionados":[{"data":"2016-01-07 00:00:00.0","fase":"Empenho","documento":"2016NE800027","caminho":"empenho?documento=153048152252016NE800027","instancia":"153048152252016NE800027","especie":"Original","valor":"8011.0400"}],"subitems":[]},{"fase":"Pagamento","documento":"2016GR800033","tipoDocumento":"Guia de  Recolhimento da União (GR)","data":"2016-01-29 00:00:00.0","orgaoSuperior":{"codigo":"26000","rotulo":"MINISTERIO DA EDUCACAO"},"orgao":{"codigo":"26234","rotulo":"UNIVERSIDADE FEDERAL DO ESPIRITO SANTO"},"unidadeGestora":{"codigo":"153046","rotulo":"UNIVERSIDADE FEDERAL DO ESPIRITO SANTO"},"gestao":{"codigo":"15225","rotulo":"UNIVERSIDADE FEDERAL DO ESPIRITO SANTO"},"favorecido":{"codigo":"1530461522","rotulo":"UNIVERSIDADE FEDERAL DO ESPIRITO SANTO"},"valor":"R$ 6.0000","observacao":"RETENÇÃO DE MULTA REF.NF.861 DE 15/12/2015, COM 10 POR CENTO DE MULTA, R$ 6,00, REF.30 DIAS DE ATRASO, PROTOCOLADO 701092/2016-35, PROCESSO 09170/2015-65.","classificacaoEconomica":{"codigo":"3","rotulo":" Despesas Correntes"},"grupoDespesa":{"codigo":"3","rotulo":" Outras Despesas Correntes"},"modalidadeAplicacao":{"codigo":"90","rotulo":"Aplic. Diretas                                                (Gastos Diretos do Governo Federal)"},"elementoDespesa":{"codigo":"30","rotulo":"MATERIAL DE CONSUMO"},"documentosRelacionados":[{"data":"2015-11-03 00:00:00.0","fase":"Empenho","documento":"2015NE802555","caminho":"empenho?documento=153046152252015NE802555","instancia":"153046152252015NE802555","especie":"Original","valor":"2498.0700"}],"subitems":[]},{"fase":"Pagamento","documento":"2016OB800469","tipoDocumento":"Ordem Bancária Lista (OB)","data":"2016-01-28 00:00:00.0","orgaoSuperior":{"codigo":"26000","rotulo":"MINISTERIO DA EDUCACAO"},"orgao":{"codigo":"26234","rotulo":"UNIVERSIDADE FEDERAL DO ESPIRITO SANTO"},"unidadeGestora":{"codigo":"153046","rotulo":"UNIVERSIDADE FEDERAL DO ESPIRITO SANTO"},"gestao":{"codigo":"15225","rotulo":"UNIVERSIDADE FEDERAL DO ESPIRITO SANTO"},"valor":"R$ 3257.8800","observacao":"RECOLHIMENTO DE ISS REF.NF.1880 DE 17/11/2015, CONTRATO 96/2013, CONTRATO 96/2013, PREFEITURA MUNICIPAL DE ALEGRE (MULTA E JUROS R$ 500,94), PROCESSO 10966/2012-18.","classificacaoEconomica":{"codigo":"3","rotulo":" Despesas Correntes"},"grupoDespesa":{"codigo":"3","rotulo":" Outras Despesas Correntes"},"modalidadeAplicacao":{"codigo":"90","rotulo":"Aplic. Diretas                                                (Gastos Diretos do Governo Federal)"},"elementoDespesa":{"codigo":"92","rotulo":"DESPESAS DE EXERCICIOS ANTERIORES"},"documentosRelacionados":[{"data":"2016-01-22 00:00:00.0","fase":"Empenho","documento":"2016NE800072","caminho":"empenho?documento=153046152252016NE800072","instancia":"153046152252016NE800072","especie":"Original","valor":"854068.2900"}],"subitems":[]},{"fase":"Pagamento","documento":"2016OB800464","tipoDocumento":"Ordem Bancária (OB)","data":"2016-01-28 00:00:00.0","orgaoSuperior":{"codigo":"26000","rotulo":"MINISTERIO DA EDUCACAO"},"orgao":{"codigo":"26234","rotulo":"UNIVERSIDADE FEDERAL DO ESPIRITO SANTO"},"unidadeGestora":{"codigo":"153046","rotulo":"UNIVERSIDADE FEDERAL DO ESPIRITO SANTO"},"gestao":{"codigo":"15225","rotulo":"UNIVERSIDADE FEDERAL DO ESPIRITO SANTO"},"favorecido":{"codigo":"00.000.000/0001-9","rotulo":"BANCO DO BRASIL SA"},"valor":"R$ 4821.2800","observacao":"RECOLHIMENTO DE ISS RETIDO S/NF 1882 EMISSAO 17/11/2015, CONTRATO 96/2013 CFE PROC.10966/2012-18.","classificacaoEconomica":{"codigo":"3","rotulo":" Despesas Correntes"},"grupoDespesa":{"codigo":"3","rotulo":" Outras Despesas Correntes"},"modalidadeAplicacao":{"codigo":"90","rotulo":"Aplic. Diretas                                                (Gastos Diretos do Governo Federal)"},"elementoDespesa":{"codigo":"92","rotulo":"DESPESAS DE EXERCICIOS ANTERIORES"},"documentosRelacionados":[{"data":"2016-01-22 00:00:00.0","fase":"Empenho","documento":"2016NE800072","caminho":"empenho?documento=153046152252016NE800072","instancia":"153046152252016NE800072","especie":"Original","valor":"854068.2900"},{"data":"2016-01-28 00:00:00.0","fase":"Pagamento","documento":"2016OB000002","caminho":"pagamento?documento=153046152252016OB000002","instancia":"153046152252016OB000002","especie":"OBS DE CANCELAMENTO DE OB DE CONTA UNICA","valor":"4821.2800"}],"subitems":[]},{"fase":"Pagamento","documento":"2016DF800097","tipoDocumento":"Documento de Arrecadação de Receitas Federais (DARF) (DF)","data":"2016-01-28 00:00:00.0","orgaoSuperior":{"codigo":"26000","rotulo":"MINISTERIO DA EDUCACAO"},"orgao":{"codigo":"26234","rotulo":"UNIVERSIDADE FEDERAL DO ESPIRITO SANTO"},"unidadeGestora":{"codigo":"153046","rotulo":"UNIVERSIDADE FEDERAL DO ESPIRITO SANTO"},"gestao":{"codigo":"15225","rotulo":"UNIVERSIDADE FEDERAL DO ESPIRITO SANTO"},"favorecido":{"codigo":"61.797.924/0001-5","rotulo":"HEWLETT-PACKARD BRASIL LTDA"},"valor":"R$ 1520.3000","observacao":"RECOLHIMENTO DE IMPOSTO REF.NF.340485 DE 16/10/2015, CONTRATO 05/2015, PROCESSO 13064/2014-03.","classificacaoEconomica":{"codigo":"3","rotulo":" Despesas Correntes"},"grupoDespesa":{"codigo":"3","rotulo":" Outras Despesas Correntes"},"modalidadeAplicacao":{"codigo":"90","rotulo":"Aplic. Diretas                                                (Gastos Diretos do Governo Federal)"},"elementoDespesa":{"codigo":"92","rotulo":"DESPESAS DE EXERCICIOS ANTERIORES"},"documentosRelacionados":[{"data":"2016-01-26 00:00:00.0","fase":"Empenho","documento":"2016NE800087","caminho":"empenho?documento=153046152252016NE800087","instancia":"153046152252016NE800087","especie":"Original","valor":"16087.8000"}],"subitems":[]},{"fase":"Pagamento","documento":"2016OB800472","tipoDocumento":"Ordem Bancária Lista (OB)","data":"2016-01-28 00:00:00.0","orgaoSuperior":{"codigo":"26000","rotulo":"MINISTERIO DA EDUCACAO"},"orgao":{"codigo":"26234","rotulo":"UNIVERSIDADE FEDERAL DO ESPIRITO SANTO"},"unidadeGestora":{"codigo":"153046","rotulo":"UNIVERSIDADE FEDERAL DO ESPIRITO SANTO"},"gestao":{"codigo":"15225","rotulo":"UNIVERSIDADE FEDERAL DO ESPIRITO SANTO"},"valor":"R$ 3145.8000","observacao":"PAGAMENTO REF. SERVICOS PRESTADOS S/VINCULO EMPREGATICIO POR ELISANGELA SANTOS PINTO MARTINS E OUTROS NO VEST 2016, INSS JAN/2016, PROTOCOLADO 701595/2016-19, PROCESSO 16001/2015-81.","classificacaoEconomica":{"codigo":"3","rotulo":" Despesas Correntes"},"grupoDespesa":{"codigo":"3","rotulo":" Outras Despesas Correntes"},"modalidadeAplicacao":{"codigo":"90","rotulo":"Aplic. Diretas                                                (Gastos Diretos do Governo Federal)"},"elementoDespesa":{"codigo":"36","rotulo":"OUTROS SERVICOS DE TERCEIROS - PESSOA FISICA"},"documentosRelacionados":[{"data":"2015-10-26 00:00:00.0","fase":"Empenho","documento":"2015NE001190","caminho":"empenho?documento=153046152252015NE001190","instancia":"153046152252015NE001190","especie":"Original","valor":"613000.0000"}],"subitems":[{"documento":"2015NE001190","instancia":"153046152252015NE001190","codigo":"28","rotulo":"SERVICO DE SELECAO E TREINAMENTO","valor":"3145.8000"}]},{"fase":"Pagamento","documento":"2016OB800465","tipoDocumento":"Ordem Bancária (OB)","data":"2016-01-28 00:00:00.0","orgaoSuperior":{"codigo":"26000","rotulo":"MINISTERIO DA EDUCACAO"},"orgao":{"codigo":"26234","rotulo":"UNIVERSIDADE FEDERAL DO ESPIRITO SANTO"},"unidadeGestora":{"codigo":"153046","rotulo":"UNIVERSIDADE FEDERAL DO ESPIRITO SANTO"},"gestao":{"codigo":"15225","rotulo":"UNIVERSIDADE FEDERAL DO ESPIRITO SANTO"},"favorecido":{"codigo":"00.360.305/0001-0","rotulo":"CAIXA ECONOMICA FEDERAL"},"valor":"R$ 4821.2800","observacao":"RECOLHIMENTO DE ISS RETIDO S/NF 1882 EMISSAO 17/11/2015, CONTRATO 96/2013 CFE PROC.10966/2012-18.","classificacaoEconomica":{"codigo":"3","rotulo":" Despesas Correntes"},"grupoDespesa":{"codigo":"3","rotulo":" Outras Despesas Correntes"},"modalidadeAplicacao":{"codigo":"90","rotulo":"Aplic. Diretas                                                (Gastos Diretos do Governo Federal)"},"elementoDespesa":{"codigo":"92","rotulo":"DESPESAS DE EXERCICIOS ANTERIORES"},"documentosRelacionados":[{"data":"2016-01-22 00:00:00.0","fase":"Empenho","documento":"2016NE800072","caminho":"empenho?documento=153046152252016NE800072","instancia":"153046152252016NE800072","especie":"Original","valor":"854068.2900"}],"subitems":[]},{"fase":"Pagamento","documento":"2016OB800461","tipoDocumento":"Ordem Bancária Lista (OB)","data":"2016-01-28 00:00:00.0","orgaoSuperior":{"codigo":"26000","rotulo":"MINISTERIO DA EDUCACAO"},"orgao":{"codigo":"26234","rotulo":"UNIVERSIDADE FEDERAL DO ESPIRITO SANTO"},"unidadeGestora":{"codigo":"153046","rotulo":"UNIVERSIDADE FEDERAL DO ESPIRITO SANTO"},"gestao":{"codigo":"15225","rotulo":"UNIVERSIDADE FEDERAL DO ESPIRITO SANTO"},"valor":"R$ 2032.2000","observacao":"RECOLHIMENTO DE ISS RETIDO S/NFS 1940 EMISSAO 18/12/2015, CONTRATO 96/2013 CFE PROC.10966/2012-18.","classificacaoEconomica":{"codigo":"3","rotulo":" Despesas Correntes"},"grupoDespesa":{"codigo":"3","rotulo":" Outras Despesas Correntes"},"modalidadeAplicacao":{"codigo":"90","rotulo":"Aplic. Diretas                                                (Gastos Diretos do Governo Federal)"},"elementoDespesa":{"codigo":"92","rotulo":"DESPESAS DE EXERCICIOS ANTERIORES"},"documentosRelacionados":[{"data":"2016-01-22 00:00:00.0","fase":"Empenho","documento":"2016NE800074","caminho":"empenho?documento=153046152252016NE800074","instancia":"153046152252016NE800074","especie":"Original","valor":"854068.2900"}],"subitems":[]},{"fase":"Pagamento","documento":"2016OB800463","tipoDocumento":"Ordem Bancária Lista (OB)","data":"2016-01-28 00:00:00.0","orgaoSuperior":{"codigo":"26000","rotulo":"MINISTERIO DA EDUCACAO"},"orgao":{"codigo":"26234","rotulo":"UNIVERSIDADE FEDERAL DO ESPIRITO SANTO"},"unidadeGestora":{"codigo":"153046","rotulo":"UNIVERSIDADE FEDERAL DO ESPIRITO SANTO"},"gestao":{"codigo":"15225","rotulo":"UNIVERSIDADE FEDERAL DO ESPIRITO SANTO"},"valor":"R$ 2267.5300","observacao":"RECOLHIMENTO DE ISS RETIDO S/NFS 1881 EMISSAO 17/11/2015, CONTRATO 96/2013 CFE PROC.10966/2012-18.","classificacaoEconomica":{"codigo":"3","rotulo":" Despesas Correntes"},"grupoDespesa":{"codigo":"3","rotulo":" Outras Despesas Correntes"},"modalidadeAplicacao":{"codigo":"90","rotulo":"Aplic. Diretas                                                (Gastos Diretos do Governo Federal)"},"elementoDespesa":{"codigo":"92","rotulo":"DESPESAS DE EXERCICIOS ANTERIORES"},"documentosRelacionados":[{"data":"2016-01-22 00:00:00.0","fase":"Empenho","documento":"2016NE800072","caminho":"empenho?documento=153046152252016NE800072","instancia":"153046152252016NE800072","especie":"Original","valor":"854068.2900"}],"subitems":[]},{"fase":"Pagamento","documento":"2016OB800468","tipoDocumento":"Ordem Bancária (OB)","data":"2016-01-28 00:00:00.0","orgaoSuperior":{"codigo":"26000","rotulo":"MINISTERIO DA EDUCACAO"},"orgao":{"codigo":"26234","rotulo":"UNIVERSIDADE FEDERAL DO ESPIRITO SANTO"},"unidadeGestora":{"codigo":"153046","rotulo":"UNIVERSIDADE FEDERAL DO ESPIRITO SANTO"},"gestao":{"codigo":"15225","rotulo":"UNIVERSIDADE FEDERAL DO ESPIRITO SANTO"},"favorecido":{"codigo":"05.038.264/0001-5","rotulo":"AREMBEPE CONSULTORIA E TREINAMENTO LTDA"},"valor":"R$ 2020.0200","observacao":"PAGAMENTO REF. NF.2234 EMISSAO 07/01/2016, CONTRATO 93/2015 CFE PROC.12387/2015-52.","classificacaoEconomica":{"codigo":"3","rotulo":" Despesas Correntes"},"grupoDespesa":{"codigo":"3","rotulo":" Outras Despesas Correntes"},"modalidadeAplicacao":{"codigo":"90","rotulo":"Aplic. Diretas                                                (Gastos Diretos do Governo Federal)"},"elementoDespesa":{"codigo":"39","rotulo":"OUTROS SERVICOS DE TERCEIROS-PESSOA JURIDICA"},"documentosRelacionados":[{"data":"2015-10-26 00:00:00.0","fase":"Empenho","documento":"2015NE802250","caminho":"empenho?documento=153046152252015NE802250","instancia":"153046152252015NE802250","especie":"Original","valor":"26769.9600"}],"subitems":[{"documento":"2015NE802250","instancia":"153046152252015NE802250","codigo":"1","rotulo":"ASSINATURAS DE PERIODICOS E ANUIDADES","valor":"2020.0200"}]},{"fase":"Pagamento","documento":"2016OB800462","tipoDocumento":"Ordem Bancária (OB)","data":"2016-01-28 00:00:00.0","orgaoSuperior":{"codigo":"26000","rotulo":"MINISTERIO DA EDUCACAO"},"orgao":{"codigo":"26234","rotulo":"UNIVERSIDADE FEDERAL DO ESPIRITO SANTO"},"unidadeGestora":{"codigo":"153046","rotulo":"UNIVERSIDADE FEDERAL DO ESPIRITO SANTO"},"gestao":{"codigo":"15225","rotulo":"UNIVERSIDADE FEDERAL DO ESPIRITO SANTO"},"favorecido":{"codigo":"00.000.000/0001-9","rotulo":"BANCO DO BRASIL SA"},"valor":"R$ 4307.8900","observacao":"RECOLHIMENTO DE ISS RETIDO S/NF 1941 EMISSAO 18/12/2015, CONTRATO 96/2013 CFE PROC.10966/2012-18.","classificacaoEconomica":{"codigo":"3","rotulo":" Despesas Correntes"},"grupoDespesa":{"codigo":"3","rotulo":" Outras Despesas Correntes"},"modalidadeAplicacao":{"codigo":"90","rotulo":"Aplic. Diretas                                                (Gastos Diretos do Governo Federal)"},"elementoDespesa":{"codigo":"92","rotulo":"DESPESAS DE EXERCICIOS ANTERIORES"},"documentosRelacionados":[{"data":"2016-01-22 00:00:00.0","fase":"Empenho","documento":"2016NE800074","caminho":"empenho?documento=153046152252016NE800074","instancia":"153046152252016NE800074","especie":"Original","valor":"854068.2900"},{"data":"2016-01-28 00:00:00.0","fase":"Pagamento","documento":"2016OB000003","caminho":"pagamento?documento=153046152252016OB000003","instancia":"153046152252016OB000003","especie":"OBS DE CANCELAMENTO DE OB DE CONTA UNICA","valor":"4307.8900"}],"subitems":[]},{"fase":"Pagamento","documento":"2016OB000002","tipoDocumento":"Ordem Bancária (OB)","data":"2016-01-28 00:00:00.0","orgaoSuperior":{"codigo":"26000","rotulo":"MINISTERIO DA EDUCACAO"},"orgao":{"codigo":"26234","rotulo":"UNIVERSIDADE FEDERAL DO ESPIRITO SANTO"},"unidadeGestora":{"codigo":"153046","rotulo":"UNIVERSIDADE FEDERAL DO ESPIRITO SANTO"},"gestao":{"codigo":"15225","rotulo":"UNIVERSIDADE FEDERAL DO ESPIRITO SANTO"},"favorecido":{"codigo":"00.000.000/0001-9","rotulo":"BANCO DO BRASIL SA"},"valor":"R$ 4821.2800","observacao":"CANCELAMENTO DA 2016OB800464.","classificacaoEconomica":{"codigo":"3","rotulo":" Despesas Correntes"},"grupoDespesa":{"codigo":"3","rotulo":" Outras Despesas Correntes"},"modalidadeAplicacao":{"codigo":"90","rotulo":"Aplic. Diretas                                                (Gastos Diretos do Governo Federal)"},"elementoDespesa":{"codigo":"92","rotulo":"DESPESAS DE EXERCICIOS ANTERIORES"},"documentosRelacionados":[{"data":"2016-01-22 00:00:00.0","fase":"Empenho","documento":"2016NE800072","caminho":"empenho?documento=153046152252016NE800072","instancia":"153046152252016NE800072","especie":"Original","valor":"854068.2900"},{"data":"2016-01-28 00:00:00.0","fase":"Pagamento","documento":"2016OB800464","caminho":"pagamento?documento=153046152252016OB800464","instancia":"153046152252016OB800464","especie":"OBB PARA MESMO BANCO/AGENCIA","valor":"4821.2800"}],"subitems":[]},{"fase":"Pagamento","documento":"2016OB800460","tipoDocumento":"Ordem Bancária (OB)","data":"2016-01-28 00:00:00.0","orgaoSuperior":{"codigo":"26000","rotulo":"MINISTERIO DA EDUCACAO"},"orgao":{"codigo":"26234","rotulo":"UNIVERSIDADE FEDERAL DO ESPIRITO SANTO"},"unidadeGestora":{"codigo":"153046","rotulo":"UNIVERSIDADE FEDERAL DO ESPIRITO SANTO"},"gestao":{"codigo":"15225","rotulo":"UNIVERSIDADE FEDERAL DO ESPIRITO SANTO"},"favorecido":{"codigo":"36.020.014/0001-1","rotulo":"EMEC - OBRAS E SERVICOS LTDA"},"valor":"R$ 37148.8200","observacao":"10 - CANCELAMENTO DA 2016OB800454 PELO GESTOR APOS REMESSA AO BANCO","classificacaoEconomica":{"codigo":"3","rotulo":" Despesas Correntes"},"grupoDespesa":{"codigo":"3","rotulo":" Outras Despesas Correntes"},"modalidadeAplicacao":{"codigo":"90","rotulo":"Aplic. Diretas                                                (Gastos Diretos do Governo Federal)"},"elementoDespesa":{"codigo":"37","rotulo":"LOCACAO DE MAO-DE-OBRA"},"documentosRelacionados":[{"data":"2016-01-26 00:00:00.0","fase":"Pagamento","documento":"2016OB800454","caminho":"pagamento?documento=153046152252016OB800454","instancia":"153046152252016OB800454","especie":"OBC/OBB PARA TERCEIROS EM OUTROS BANCOS","valor":"37148.8200"},{"data":"2015-03-10 00:00:00.0","fase":"Empenho","documento":"2015NE800367","caminho":"empenho?documento=153046152252015NE800367","instancia":"153046152252015NE800367","especie":"Original","valor":"500.0000"}],"subitems":[{"documento":"2015NE800367","instancia":"153046152252015NE800367","codigo":"2","rotulo":"LIMPEZA E CONSERVACAO","valor":"37148.8200"}]},{"fase":"Pagamento","documento":"2016OB800466","tipoDocumento":"Ordem Bancária (OB)","data":"2016-01-28 00:00:00.0","orgaoSuperior":{"codigo":"26000","rotulo":"MINISTERIO DA EDUCACAO"},"orgao":{"codigo":"26234","rotulo":"UNIVERSIDADE FEDERAL DO ESPIRITO SANTO"},"unidadeGestora":{"codigo":"153046","rotulo":"UNIVERSIDADE FEDERAL DO ESPIRITO SANTO"},"gestao":{"codigo":"15225","rotulo":"UNIVERSIDADE FEDERAL DO ESPIRITO SANTO"},"favorecido":{"codigo":"00.360.305/0001-0","rotulo":"CAIXA ECONOMICA FEDERAL"},"valor":"R$ 4307.8900","observacao":"RECOLHIMENTO DE ISS RETIDO S/NF 1941 EMISSAO 18/12/2015, CONTRATO 96/2013 CFE PROC.10966/2012-18.","classificacaoEconomica":{"codigo":"3","rotulo":" Despesas Correntes"},"grupoDespesa":{"codigo":"3","rotulo":" Outras Despesas Correntes"},"modalidadeAplicacao":{"codigo":"90","rotulo":"Aplic. Diretas                                                (Gastos Diretos do Governo Federal)"},"elementoDespesa":{"codigo":"92","rotulo":"DESPESAS DE EXERCICIOS ANTERIORES"},"documentosRelacionados":[{"data":"2016-01-22 00:00:00.0","fase":"Empenho","documento":"2016NE800074","caminho":"empenho?documento=153046152252016NE800074","instancia":"153046152252016NE800074","especie":"Original","valor":"854068.2900"}],"subitems":[]},{"fase":"Pagamento","documento":"2016OB000003","tipoDocumento":"Ordem Bancária (OB)","data":"2016-01-28 00:00:00.0","orgaoSuperior":{"codigo":"26000","rotulo":"MINISTERIO DA EDUCACAO"},"orgao":{"codigo":"26234","rotulo":"UNIVERSIDADE FEDERAL DO ESPIRITO SANTO"},"unidadeGestora":{"codigo":"153046","rotulo":"UNIVERSIDADE FEDERAL DO ESPIRITO SANTO"},"gestao":{"codigo":"15225","rotulo":"UNIVERSIDADE FEDERAL DO ESPIRITO SANTO"},"favorecido":{"codigo":"00.000.000/0001-9","rotulo":"BANCO DO BRASIL SA"},"valor":"R$ 4307.8900","observacao":"CANCELAMENTO DA 2016OB800462.","classificacaoEconomica":{"codigo":"3","rotulo":" Despesas Correntes"},"grupoDespesa":{"codigo":"3","rotulo":" Outras Despesas Correntes"},"modalidadeAplicacao":{"codigo":"90","rotulo":"Aplic. Diretas                                                (Gastos Diretos do Governo Federal)"},"elementoDespesa":{"codigo":"92","rotulo":"DESPESAS DE EXERCICIOS ANTERIORES"},"documentosRelacionados":[{"data":"2016-01-22 00:00:00.0","fase":"Empenho","documento":"2016NE800074","caminho":"empenho?documento=153046152252016NE800074","instancia":"153046152252016NE800074","especie":"Original","valor":"854068.2900"},{"data":"2016-01-28 00:00:00.0","fase":"Pagamento","documento":"2016OB800462","caminho":"pagamento?documento=153046152252016OB800462","instancia":"153046152252016OB800462","especie":"OBB PARA MESMO BANCO/AGENCIA","valor":"4307.8900"}],"subitems":[]}]