[{"fase":"Pagamento","documento":"2016OB800447","tipoDocumento":"Ordem Bancária Lista (OB)","data":"2016-01-26 00:00:00.0","orgaoSuperior":{"codigo":"26000","rotulo":"MINISTERIO DA EDUCACAO"},"orgao":{"codigo":"26234","rotulo":"UNIVERSIDADE FEDERAL DO ESPIRITO SANTO"},"unidadeGestora":{"codigo":"153046","rotulo":"UNIVERSIDADE FEDERAL DO ESPIRITO SANTO"},"gestao":{"codigo":"15225","rotulo":"UNIVERSIDADE FEDERAL DO ESPIRITO SANTO"},"valor":"R$ 22157.8000","observacao":"PAGAMENTO DE ISS SOBRE A NOTA FISCAL N.1879 DE 14/11/2015 CONFORME CONTRATO N. 96/2013 E PROCESSO N. 010966/2012-18.","classificacaoEconomica":{"codigo":"3","rotulo":" Despesas Correntes"},"grupoDespesa":{"codigo":"3","rotulo":" Outras Despesas Correntes"},"modalidadeAplicacao":{"codigo":"90","rotulo":"Aplic. Diretas                                                (Gastos Diretos do Governo Federal)"},"elementoDespesa":{"codigo":"92","rotulo":"DESPESAS DE EXERCICIOS ANTERIORES"},"documentosRelacionados":[{"data":"2016-01-22 00:00:00.0","fase":"Empenho","documento":"2016NE800072","caminho":"empenho?documento=153046152252016NE800072","instancia":"153046152252016NE800072","especie":"Original","valor":"854068.2900"}],"subitems":[]},{"fase":"Pagamento","documento":"2016DR800016","tipoDocumento":"Documento de Arrecadação dos Estados e Municípios (DAR) (DR)","data":"2016-01-26 00:00:00.0","orgaoSuperior":{"codigo":"26000","rotulo":"MINISTERIO DA EDUCACAO"},"orgao":{"codigo":"26234","rotulo":"UNIVERSIDADE FEDERAL DO ESPIRITO SANTO"},"unidadeGestora":{"codigo":"153046","rotulo":"UNIVERSIDADE FEDERAL DO ESPIRITO SANTO"},"gestao":{"codigo":"15225","rotulo":"UNIVERSIDADE FEDERAL DO ESPIRITO SANTO"},"favorecido":{"codigo":"15304","rotulo":"UNIVERSIDADE FEDERAL DO ESPIRITO SANTO"},"valor":"R$ 8058.6600","observacao":"RECOLHIMENTO DE ISS RETIDO S/NOTA FISCAL N.1942 DE 18/12/2015 CONFORME CONTRATO N. 96/2013 E PROCESSO N. 010966/2012-18.","classificacaoEconomica":{"codigo":"3","rotulo":" Despesas Correntes"},"grupoDespesa":{"codigo":"3","rotulo":" Outras Despesas Correntes"},"modalidadeAplicacao":{"codigo":"90","rotulo":"Aplic. Diretas                                                (Gastos Diretos do Governo Federal)"},"elementoDespesa":{"codigo":"92","rotulo":"DESPESAS DE EXERCICIOS ANTERIORES"},"documentosRelacionados":[{"data":"2016-01-22 00:00:00.0","fase":"Empenho","documento":"2016NE800074","caminho":"empenho?documento=153046152252016NE800074","instancia":"153046152252016NE800074","especie":"Original","valor":"854068.2900"}],"subitems":[]},{"fase":"Pagamento","documento":"2016GP800090","tipoDocumento":"Guia de Recolhimento da Previdência Social (GP)","data":"2016-01-26 00:00:00.0","orgaoSuperior":{"codigo":"26000","rotulo":"MINISTERIO DA EDUCACAO"},"orgao":{"codigo":"26234","rotulo":"UNIVERSIDADE FEDERAL DO ESPIRITO SANTO"},"unidadeGestora":{"codigo":"153046","rotulo":"UNIVERSIDADE FEDERAL DO ESPIRITO SANTO"},"gestao":{"codigo":"15225","rotulo":"UNIVERSIDADE FEDERAL DO ESPIRITO SANTO"},"favorecido":{"codigo":"25.183.468/0003-5","rotulo":"PLANTAO SERVICOS DE VIGILANCIA LTDA"},"valor":"R$ 95807.6700","observacao":"RECOLHIMENTO DE INSS RETIDO S/NNOTAS FISCAIS N.1938 A 1943 DE 18/12/2015 CONFORME CONTRATO N. 96/2013 E PROCESSO N. 010966/2012-18.","classificacaoEconomica":{"codigo":"3","rotulo":" Despesas Correntes"},"grupoDespesa":{"codigo":"3","rotulo":" Outras Despesas Correntes"},"modalidadeAplicacao":{"codigo":"90","rotulo":"Aplic. Diretas                                                (Gastos Diretos do Governo Federal)"},"elementoDespesa":{"codigo":"92","rotulo":"DESPESAS DE EXERCICIOS ANTERIORES"},"documentosRelacionados":[{"data":"2016-01-22 00:00:00.0","fase":"Empenho","documento":"2016NE800074","caminho":"empenho?documento=153046152252016NE800074","instancia":"153046152252016NE800074","especie":"Original","valor":"854068.2900"}],"subitems":[]},{"fase":"Pagamento","documento":"2016OB800442","tipoDocumento":"Ordem Bancária Lista (OB)","data":"2016-01-26 00:00:00.0","orgaoSuperior":{"codigo":"26000","rotulo":"MINISTERIO DA EDUCACAO"},"orgao":{"codigo":"26234","rotulo":"UNIVERSIDADE FEDERAL DO ESPIRITO SANTO"},"unidadeGestora":{"codigo":"153046","rotulo":"UNIVERSIDADE FEDERAL DO ESPIRITO SANTO"},"gestao":{"codigo":"15225","rotulo":"UNIVERSIDADE FEDERAL DO ESPIRITO SANTO"},"valor":"R$ 20473.1400","observacao":"PAGAMENTO REF. FATS.23001989-3 DE 10/10/15, 100204-7 DE 15/10/15, 70100205-1 DE 07/10/15, 70100164-4 DE 04/11/15 E 23001993-3 DE 10/11/15 CONF.TERMO DE RECONHECIMENTO DE DIVIDA, PROTOCOLADO 785223/2015-48, PROC.8672/2010-64.","classificacaoEconomica":{"codigo":"3","rotulo":" Despesas Correntes"},"grupoDespesa":{"codigo":"3","rotulo":" Outras Despesas Correntes"},"modalidadeAplicacao":{"codigo":"90","rotulo":"Aplic. Diretas                                                (Gastos Diretos do Governo Federal)"},"elementoDespesa":{"codigo":"93","rotulo":"INDENIZACOES E RESTITUICOES"},"documentosRelacionados":[{"data":"2016-01-07 00:00:00.0","fase":"Empenho","documento":"2016NE000119","caminho":"empenho?documento=153046152252016NE000119","instancia":"153046152252016NE000119","especie":"Original","valor":"22609.7800"}],"subitems":[{"documento":"2016NE000119","instancia":"153046152252016NE000119","codigo":"1","rotulo":"INDENIZACOES","valor":"20473.1400"}]},{"fase":"Pagamento","documento":"2016OB800449","tipoDocumento":"Ordem Bancária Lista (OB)","data":"2016-01-26 00:00:00.0","orgaoSuperior":{"codigo":"26000","rotulo":"MINISTERIO DA EDUCACAO"},"orgao":{"codigo":"26234","rotulo":"UNIVERSIDADE FEDERAL DO ESPIRITO SANTO"},"unidadeGestora":{"codigo":"153046","rotulo":"UNIVERSIDADE FEDERAL DO ESPIRITO SANTO"},"gestao":{"codigo":"15225","rotulo":"UNIVERSIDADE FEDERAL DO ESPIRITO SANTO"},"valor":"R$ 22157.8000","observacao":"PAGAMENTO DE ISS SOBRE A NOTA FISCAL N.1938 DE 18/12/2015 CONFORME CONTRATO N. 96/2013 E PROCESSO N. 010966/2012-18.","classificacaoEconomica":{"codigo":"3","rotulo":" Despesas Correntes"},"grupoDespesa":{"codigo":"3","rotulo":" Outras Despesas Correntes"},"modalidadeAplicacao":{"codigo":"90","rotulo":"Aplic. Diretas                                                (Gastos Diretos do Governo Federal)"},"elementoDespesa":{"codigo":"92","rotulo":"DESPESAS DE EXERCICIOS ANTERIORES"},"documentosRelacionados":[{"data":"2016-01-22 00:00:00.0","fase":"Empenho","documento":"2016NE800074","caminho":"empenho?documento=153046152252016NE800074","instancia":"153046152252016NE800074","especie":"Original","valor":"854068.2900"}],"subitems":[]},{"fase":"Pagamento","documento":"2016GP800089","tipoDocumento":"Guia de Recolhimento da Previdência Social (GP)","data":"2016-01-26 00:00:00.0","orgaoSuperior":{"codigo":"26000","rotulo":"MINISTERIO DA EDUCACAO"},"orgao":{"codigo":"26234","rotulo":"UNIVERSIDADE FEDERAL DO ESPIRITO SANTO"},"unidadeGestora":{"codigo":"153046","rotulo":"UNIVERSIDADE FEDERAL DO ESPIRITO SANTO"},"gestao":{"codigo":"15225","rotulo":"UNIVERSIDADE FEDERAL DO ESPIRITO SANTO"},"favorecido":{"codigo":"25.183.468/0003-5","rotulo":"PLANTAO SERVICOS DE VIGILANCIA LTDA"},"valor":"R$ 106357.9700","observacao":"RECOLHIMENTO DE INSS RETIDO S/NOTAS FISCAIS N.1879 A 1884 DE 147/11/2015 CONFORME CONTRATO N. 96/2013 E PROCESSO N. 010966/2012-18.","classificacaoEconomica":{"codigo":"3","rotulo":" Despesas Correntes"},"grupoDespesa":{"codigo":"3","rotulo":" Outras Despesas Correntes"},"modalidadeAplicacao":{"codigo":"90","rotulo":"Aplic. Diretas                                                (Gastos Diretos do Governo Federal)"},"elementoDespesa":{"codigo":"92","rotulo":"DESPESAS DE EXERCICIOS ANTERIORES"},"documentosRelacionados":[{"data":"2016-01-22 00:00:00.0","fase":"Empenho","documento":"2016NE800072","caminho":"empenho?documento=153046152252016NE800072","instancia":"153046152252016NE800072","especie":"Original","valor":"854068.2900"}],"subitems":[]},{"fase":"Pagamento","documento":"2016OB800444","tipoDocumento":"Ordem Bancária Lista (OB)","data":"2016-01-26 00:00:00.0","orgaoSuperior":{"codigo":"26000","rotulo":"MINISTERIO DA EDUCACAO"},"orgao":{"codigo":"26234","rotulo":"UNIVERSIDADE FEDERAL DO ESPIRITO SANTO"},"unidadeGestora":{"codigo":"153046","rotulo":"UNIVERSIDADE FEDERAL DO ESPIRITO SANTO"},"gestao":{"codigo":"15225","rotulo":"UNIVERSIDADE FEDERAL DO ESPIRITO SANTO"},"valor":"R$ 12700.9200","observacao":"PAGAMENTO REF.FATURAS 15/04/70100221-7, 15/04/70100220-2 E 15/04/75000228-6 DE 11/04/2015, 11/04/2015 E 08/04/2015, CONTRATO 79/2010, PROCESSO 13634/2009-90.","classificacaoEconomica":{"codigo":"3","rotulo":" Despesas Correntes"},"grupoDespesa":{"codigo":"3","rotulo":" Outras Despesas Correntes"},"modalidadeAplicacao":{"codigo":"90","rotulo":"Aplic. Diretas                                                (Gastos Diretos do Governo Federal)"},"elementoDespesa":{"codigo":"39","rotulo":"OUTROS SERVICOS DE TERCEIROS-PESSOA JURIDICA"},"documentosRelacionados":[{"data":"2015-02-09 00:00:00.0","fase":"Empenho","documento":"2015NE800204","caminho":"empenho?documento=153046152252015NE800204","instancia":"153046152252015NE800204","especie":"Original","valor":"100.0000"},{"data":"2015-02-09 00:00:00.0","fase":"Empenho","documento":"2015NE800205","caminho":"empenho?documento=153046152252015NE800205","instancia":"153046152252015NE800205","especie":"Original","valor":"100.0000"}],"subitems":[{"documento":"2015NE800204","instancia":"153046152252015NE800204","codigo":"58","rotulo":"SERVICOS DE TELECOMUNICACOES","valor":"8025.4500"},{"documento":"2015NE800205","instancia":"153046152252015NE800205","codigo":"58","rotulo":"SERVICOS DE TELECOMUNICACOES","valor":"4675.4700"}]},{"fase":"Pagamento","documento":"2016OB800454","tipoDocumento":"Ordem Bancária (OB)","data":"2016-01-26 00:00:00.0","orgaoSuperior":{"codigo":"26000","rotulo":"MINISTERIO DA EDUCACAO"},"orgao":{"codigo":"26234","rotulo":"UNIVERSIDADE FEDERAL DO ESPIRITO SANTO"},"unidadeGestora":{"codigo":"153046","rotulo":"UNIVERSIDADE FEDERAL DO ESPIRITO SANTO"},"gestao":{"codigo":"15225","rotulo":"UNIVERSIDADE FEDERAL DO ESPIRITO SANTO"},"favorecido":{"codigo":"36.020.014/0001-1","rotulo":"EMEC - OBRAS E SERVICOS LTDA"},"valor":"R$ 37148.8200","observacao":"LIQUIDACAO REF. NFS 609 E 610 EMISSAO 22/09/2015, CONTRATO 42/2015, PROTOCOLADO 761990/2015-61 CFE PROC.15778/2014-48.","classificacaoEconomica":{"codigo":"3","rotulo":" Despesas Correntes"},"grupoDespesa":{"codigo":"3","rotulo":" Outras Despesas Correntes"},"modalidadeAplicacao":{"codigo":"90","rotulo":"Aplic. Diretas                                                (Gastos Diretos do Governo Federal)"},"elementoDespesa":{"codigo":"37","rotulo":"LOCACAO DE MAO-DE-OBRA"},"documentosRelacionados":[{"data":"2016-01-28 00:00:00.0","fase":"Pagamento","documento":"2016OB800460","caminho":"pagamento?documento=153046152252016OB800460","instancia":"153046152252016OB800460","especie":"OBS DE OUTRAS CONTAS PARA CONTA UNICA","valor":"37148.8200"},{"data":"2015-03-10 00:00:00.0","fase":"Empenho","documento":"2015NE800367","caminho":"empenho?documento=153046152252015NE800367","instancia":"153046152252015NE800367","especie":"Original","valor":"500.0000"}],"subitems":[{"documento":"2015NE800367","instancia":"153046152252015NE800367","codigo":"2","rotulo":"LIMPEZA E CONSERVACAO","valor":"37148.8200"}]},{"fase":"Pagamento","documento":"2016OB800448","tipoDocumento":"Ordem Bancária Lista (OB)","data":"2016-01-26 00:00:00.0","orgaoSuperior":{"codigo":"26000","rotulo":"MINISTERIO DA EDUCACAO"},"orgao":{"codigo":"26234","rotulo":"UNIVERSIDADE FEDERAL DO ESPIRITO SANTO"},"unidadeGestora":{"codigo":"153046","rotulo":"UNIVERSIDADE FEDERAL DO ESPIRITO SANTO"},"gestao":{"codigo":"15225","rotulo":"UNIVERSIDADE FEDERAL DO ESPIRITO SANTO"},"valor":"R$ 2524.0800","observacao":"PAGAMENTO DE ISS SOBRE A NOTA FISCAL N.1884 DE 14/11/2015 CONFORME CONTRATO N. 96/2013 E PROCESSO N. 010966/2012-18.","classificacaoEconomica":{"codigo":"3","rotulo":" Despesas Correntes"},"grupoDespesa":{"codigo":"3","rotulo":" Outras Despesas Correntes"},"modalidadeAplicacao":{"codigo":"90","rotulo":"Aplic. Diretas                                                (Gastos Diretos do Governo Federal)"},"elementoDespesa":{"codigo":"92","rotulo":"DESPESAS DE EXERCICIOS ANTERIORES"},"documentosRelacionados":[{"data":"2016-01-22 00:00:00.0","fase":"Empenho","documento":"2016NE800072","caminho":"empenho?documento=153046152252016NE800072","instancia":"153046152252016NE800072","especie":"Original","valor":"854068.2900"}],"subitems":[]},{"fase":"Pagamento","documento":"2016DF800094","tipoDocumento":"Documento de Arrecadação de Receitas Federais (DARF) (DF)","data":"2016-01-26 00:00:00.0","orgaoSuperior":{"codigo":"26000","rotulo":"MINISTERIO DA EDUCACAO"},"orgao":{"codigo":"26234","rotulo":"UNIVERSIDADE FEDERAL DO ESPIRITO SANTO"},"unidadeGestora":{"codigo":"153046","rotulo":"UNIVERSIDADE FEDERAL DO ESPIRITO SANTO"},"gestao":{"codigo":"15225","rotulo":"UNIVERSIDADE FEDERAL DO ESPIRITO SANTO"},"favorecido":{"codigo":"57.135.675/0001-6","rotulo":"COMERCIAL LENA LTDA ME"},"valor":"R$ 15881.0700","observacao":"RECOLHIMENTO DE IMPOSTO REF.NF.61 DE 15/01/2016, CONTRATO 1011/2014, PROTOCOLADO 701866/2016-28, PROCESSO 12015/2013-64.","classificacaoEconomica":{"codigo":"3","rotulo":" Despesas Correntes"},"grupoDespesa":{"codigo":"3","rotulo":" Outras Despesas Correntes"},"modalidadeAplicacao":{"codigo":"90","rotulo":"Aplic. Diretas                                                (Gastos Diretos do Governo Federal)"},"elementoDespesa":{"codigo":"39","rotulo":"OUTROS SERVICOS DE TERCEIROS-PESSOA JURIDICA"},"documentosRelacionados":[{"data":"2015-02-06 00:00:00.0","fase":"Empenho","documento":"2015NE800193","caminho":"empenho?documento=153046152252015NE800193","instancia":"153046152252015NE800193","especie":"Original","valor":"100.0000"}],"subitems":[]},{"fase":"Pagamento","documento":"2016OB800451","tipoDocumento":"Ordem Bancária Lista (OB)","data":"2016-01-26 00:00:00.0","orgaoSuperior":{"codigo":"26000","rotulo":"MINISTERIO DA EDUCACAO"},"orgao":{"codigo":"26234","rotulo":"UNIVERSIDADE FEDERAL DO ESPIRITO SANTO"},"unidadeGestora":{"codigo":"153046","rotulo":"UNIVERSIDADE FEDERAL DO ESPIRITO SANTO"},"gestao":{"codigo":"15225","rotulo":"UNIVERSIDADE FEDERAL DO ESPIRITO SANTO"},"valor":"R$ 2293.4300","observacao":"PAGAMENTO DE ISS SOBRE A NOTA FISCAL N.1943 DE 18/12/2015 CONFORME CONTRATO N. 96/2013 E PROCESSO N. 010966/2012-18.","classificacaoEconomica":{"codigo":"3","rotulo":" Despesas Correntes"},"grupoDespesa":{"codigo":"3","rotulo":" Outras Despesas Correntes"},"modalidadeAplicacao":{"codigo":"90","rotulo":"Aplic. Diretas                                                (Gastos Diretos do Governo Federal)"},"elementoDespesa":{"codigo":"92","rotulo":"DESPESAS DE EXERCICIOS ANTERIORES"},"documentosRelacionados":[{"data":"2016-01-22 00:00:00.0","fase":"Empenho","documento":"2016NE800074","caminho":"empenho?documento=153046152252016NE800074","instancia":"153046152252016NE800074","especie":"Original","valor":"854068.2900"}],"subitems":[]},{"fase":"Pagamento","documento":"2016DR800015","tipoDocumento":"Documento de Arrecadação dos Estados e Municípios (DAR) (DR)","data":"2016-01-26 00:00:00.0","orgaoSuperior":{"codigo":"26000","rotulo":"MINISTERIO DA EDUCACAO"},"orgao":{"codigo":"26234","rotulo":"UNIVERSIDADE FEDERAL DO ESPIRITO SANTO"},"unidadeGestora":{"codigo":"153046","rotulo":"UNIVERSIDADE FEDERAL DO ESPIRITO SANTO"},"gestao":{"codigo":"15225","rotulo":"UNIVERSIDADE FEDERAL DO ESPIRITO SANTO"},"favorecido":{"codigo":"15304","rotulo":"UNIVERSIDADE FEDERAL DO ESPIRITO SANTO"},"valor":"R$ 8058.6600","observacao":"RECOLHIMENTO DE ISS RETIDO S/NOTA FISCAL N.1883 DE 17/11/2015 CONFORME CONTRATO N. 96/2013 E PROCESSO N. 010966/2012-18.","classificacaoEconomica":{"codigo":"3","rotulo":" Despesas Correntes"},"grupoDespesa":{"codigo":"3","rotulo":" Outras Despesas Correntes"},"modalidadeAplicacao":{"codigo":"90","rotulo":"Aplic. Diretas                                                (Gastos Diretos do Governo Federal)"},"elementoDespesa":{"codigo":"92","rotulo":"DESPESAS DE EXERCICIOS ANTERIORES"},"documentosRelacionados":[{"data":"2016-01-22 00:00:00.0","fase":"Empenho","documento":"2016NE800072","caminho":"empenho?documento=153046152252016NE800072","instancia":"153046152252016NE800072","especie":"Original","valor":"854068.2900"}],"subitems":[]},{"fase":"Pagamento","documento":"2016OB800452","tipoDocumento":"Ordem Bancária Lista (OB)","data":"2016-01-26 00:00:00.0","orgaoSuperior":{"codigo":"26000","rotulo":"MINISTERIO DA EDUCACAO"},"orgao":{"codigo":"26234","rotulo":"UNIVERSIDADE FEDERAL DO ESPIRITO SANTO"},"unidadeGestora":{"codigo":"153046","rotulo":"UNIVERSIDADE FEDERAL DO ESPIRITO SANTO"},"gestao":{"codigo":"15225","rotulo":"UNIVERSIDADE FEDERAL DO ESPIRITO SANTO"},"valor":"R$ 7714.2300","observacao":"RECOLHIMENTO DE ISS RETIDO REF. NF.101 EMISSAO 14/12/2015, CONTRATO 152/2012 CFE PROC.23896/2013-49.","classificacaoEconomica":{"codigo":"4","rotulo":" Despesas de Capital"},"grupoDespesa":{"codigo":"4","rotulo":" Investimentos"},"modalidadeAplicacao":{"codigo":"90","rotulo":"Aplic. Diretas                                                (Gastos Diretos do Governo Federal)"},"elementoDespesa":{"codigo":"92","rotulo":"DESPESAS DE EXERCICIOS ANTERIORES"},"documentosRelacionados":[{"data":"2016-01-21 00:00:00.0","fase":"Empenho","documento":"2016NE800080","caminho":"empenho?documento=153046152252016NE800080","instancia":"153046152252016NE800080","especie":"Original","valor":"199334.0300"}],"subitems":[]},{"fase":"Pagamento","documento":"2016OB800450","tipoDocumento":"Ordem Bancária Lista (OB)","data":"2016-01-26 00:00:00.0","orgaoSuperior":{"codigo":"26000","rotulo":"MINISTERIO DA EDUCACAO"},"orgao":{"codigo":"26234","rotulo":"UNIVERSIDADE FEDERAL DO ESPIRITO SANTO"},"unidadeGestora":{"codigo":"153046","rotulo":"UNIVERSIDADE FEDERAL DO ESPIRITO SANTO"},"gestao":{"codigo":"15225","rotulo":"UNIVERSIDADE FEDERAL DO ESPIRITO SANTO"},"valor":"R$ 2920.9800","observacao":"PAGAMENTO DE ISS SOBRE A NOTA FISCAL N.1939 DE 18/12/2015 CONFORME CONTRATO N. 96/2013 E PROCESSO N. 010966/2012-18.","classificacaoEconomica":{"codigo":"3","rotulo":" Despesas Correntes"},"grupoDespesa":{"codigo":"3","rotulo":" Outras Despesas Correntes"},"modalidadeAplicacao":{"codigo":"90","rotulo":"Aplic. Diretas                                                (Gastos Diretos do Governo Federal)"},"elementoDespesa":{"codigo":"92","rotulo":"DESPESAS DE EXERCICIOS ANTERIORES"},"documentosRelacionados":[{"data":"2016-01-22 00:00:00.0","fase":"Empenho","documento":"2016NE800074","caminho":"empenho?documento=153046152252016NE800074","instancia":"153046152252016NE800074","especie":"Original","valor":"854068.2900"}],"subitems":[]},{"fase":"Pagamento","documento":"2016GP800091","tipoDocumento":"Guia de Recolhimento da Previdência Social (GP)","data":"2016-01-26 00:00:00.0","orgaoSuperior":{"codigo":"26000","rotulo":"MINISTERIO DA EDUCACAO"},"orgao":{"codigo":"26234","rotulo":"UNIVERSIDADE FEDERAL DO ESPIRITO SANTO"},"unidadeGestora":{"codigo":"153046","rotulo":"UNIVERSIDADE FEDERAL DO ESPIRITO SANTO"},"gestao":{"codigo":"15225","rotulo":"UNIVERSIDADE FEDERAL DO ESPIRITO SANTO"},"favorecido":{"codigo":"14.277.035/0001-8","rotulo":"ROCHA ELETRICA E EDIFICACOES LTDA - ME"},"valor":"R$ 11180.4400","observacao":"RECOLHIMENTO DE INSS RETIDO REF. NF.101 EMISSAO 14/12/2015, CONTRATO 152/2012 CFE PROC.23896/2013-49.","classificacaoEconomica":{"codigo":"4","rotulo":" Despesas de Capital"},"grupoDespesa":{"codigo":"4","rotulo":" Investimentos"},"modalidadeAplicacao":{"codigo":"90","rotulo":"Aplic. Diretas                                                (Gastos Diretos do Governo Federal)"},"elementoDespesa":{"codigo":"92","rotulo":"DESPESAS DE EXERCICIOS ANTERIORES"},"documentosRelacionados":[{"data":"2016-01-21 00:00:00.0","fase":"Empenho","documento":"2016NE800080","caminho":"empenho?documento=153046152252016NE800080","instancia":"153046152252016NE800080","especie":"Original","valor":"199334.0300"}],"subitems":[]}]